swagenttools/__init__.py
swagenttools/extractor.py
swagenttools/seeker.py
swagenttools/sql_engine.py
swagenttools/sql_functions/swagent_main_db_create.sql
swagenttools/user_agent_list/Android.txt
swagenttools/user_agent_list/Chrome.txt
swagenttools/user_agent_list/Edge.txt
swagenttools/user_agent_list/Firefox.txt
swagenttools/user_agent_list/LICENSE
swagenttools/user_agent_list/Opera.txt
swagenttools/user_agent_list/README.md
swagenttools/user_agent_list/Safari.txt
swagenttools-0.3.20.dist-info/LICENSE
swagenttools-0.3.20.dist-info/METADATA
swagenttools-0.3.20.dist-info/WHEEL
swagenttools-0.3.20.dist-info/RECORD
