Metadata-Version: 2.1
Name: swagenttools
Version: 0.3.20
Summary: A small crawler to scrape data from swranking.com and store in in the local db of the vm.
License: MIT
Author: Axel Tessai
Author-email: aahern@ucdavis.edu
Requires-Python: >=3.7
Classifier: License :: OSI Approved :: MIT License
Classifier: Operating System :: OS Independent
Classifier: Programming Language :: Python :: 3
Classifier: Programming Language :: Python :: 3.7
Classifier: Programming Language :: Python :: 3.8
Classifier: Programming Language :: Python :: 3.9
Classifier: Programming Language :: Python :: 3.10
Classifier: Programming Language :: Python :: 3.11
Classifier: Programming Language :: Python :: 3
